#ifndef _AVM_OPCODES_H_
#define _AVM_OPCODES_H_

#define j_nop                0x00  /*  00 */   
#define j_aconst_null        0x01  /*  01 */   
#define j_iconst_m1          0x02  /*  02 */   
#define j_iconst_0           0x03  /*  03 */   
#define j_iconst_1           0x04  /*  04 */   
#define j_iconst_2           0x05  /*  05 */   
#define j_iconst_3           0x06  /*  06 */   
#define j_iconst_4           0x07  /*  07 */   
#define j_iconst_5           0x08  /*  08 */   
#define j_lconst_0           0x09  /*  09 */   
#define j_lconst_1           0x0a  /*  10 */   
#define j_fconst_0           0x0b  /*  11 */   
#define j_fconst_1           0x0c  /*  12 */   
#define j_fconst_2           0x0d  /*  13 */   
#define j_dconst_0           0x0e  /*  14 */   
#define j_dconst_1           0x0f  /*  15 */   
#define j_bipush             0x10  /*  16 */   
#define j_sipush             0x11  /*  17 */   
#define j_ldc                0x12  /*  18 */   
#define j_ldc_w              0x13  /*  19 */   
#define j_ldc2_w             0x14  /*  20 */   
#define j_iload              0x15  /*  21 */   
#define j_lload              0x16  /*  22 */   
#define j_fload              0x17  /*  23 */   
#define j_dload              0x18  /*  24 */   
#define j_aload              0x19  /*  25 */   
#define j_iload_0            0x1a  /*  26 */   
#define j_iload_1            0x1b  /*  27 */   
#define j_iload_2            0x1c  /*  28 */   
#define j_iload_3            0x1d  /*  29 */   
#define j_lload_0            0x1e  /*  30 */   
#define j_lload_1            0x1f  /*  31 */   
#define j_lload_2            0x20  /*  32 */   
#define j_lload_3            0x21  /*  33 */   
#define j_fload_0            0x22  /*  34 */   
#define j_fload_1            0x23  /*  35 */   
#define j_fload_2            0x24  /*  36 */   
#define j_fload_3            0x25  /*  37 */   
#define j_dload_0            0x26  /*  38 */   
#define j_dload_1            0x27  /*  39 */   
#define j_dload_2            0x28  /*  40 */   
#define j_dload_3            0x29  /*  41 */   
#define j_aload_0            0x2a  /*  42 */   
#define j_aload_1            0x2b  /*  43 */   
#define j_aload_2            0x2c  /*  44 */   
#define j_aload_3            0x2d  /*  45 */   
#define j_iaload             0x2e  /*  46 */   
#define j_laload             0x2f  /*  47 */   
#define j_faload             0x30  /*  48 */   
#define j_daload             0x31  /*  49 */   
#define j_aaload             0x32  /*  50 */   
#define j_baload             0x33  /*  51 */   
#define j_caload             0x34  /*  52 */   
#define j_saload             0x35  /*  53 */   
#define j_istore             0x36  /*  54 */   
#define j_lstore             0x37  /*  55 */   
#define j_fstore             0x38  /*  56 */   
#define j_dstore             0x39  /*  57 */   
#define j_astore             0x3a  /*  58 */   
#define j_istore_0           0x3b  /*  59 */   
#define j_istore_1           0x3c  /*  60 */   
#define j_istore_2           0x3d  /*  61 */   
#define j_istore_3           0x3e  /*  62 */   
#define j_lstore_0           0x3f  /*  63 */   
#define j_lstore_1           0x40  /*  64 */   
#define j_lstore_2           0x41  /*  65 */   
#define j_lstore_3           0x42  /*  66 */   
#define j_fstore_0           0x43  /*  67 */   
#define j_fstore_1           0x44  /*  68 */   
#define j_fstore_2           0x45  /*  69 */   
#define j_fstore_3           0x46  /*  70 */   
#define j_dstore_0           0x47  /*  71 */   
#define j_dstore_1           0x48  /*  72 */   
#define j_dstore_2           0x49  /*  73 */   
#define j_dstore_3           0x4a  /*  74 */   
#define j_astore_0           0x4b  /*  75 */   
#define j_astore_1           0x4c  /*  76 */   
#define j_astore_2           0x4d  /*  77 */   
#define j_astore_3           0x4e  /*  78 */   
#define j_iastore            0x4f  /*  79 */   
#define j_lastore            0x50  /*  80 */   
#define j_fastore            0x51  /*  81 */   
#define j_dastore            0x52  /*  82 */   
#define j_aastore            0x53  /*  83 */   
#define j_bastore            0x54  /*  84 */   
#define j_castore            0x55  /*  85 */   
#define j_sastore            0x56  /*  86 */   
#define j_pop                0x57  /*  87 */   
#define j_pop2               0x58  /*  88 */   
#define j_dup                0x59  /*  89 */   
#define j_dup_x1             0x5a  /*  90 */   
#define j_dup_x2             0x5b  /*  91 */   
#define j_dup2               0x5c  /*  92 */   
#define j_dup2_x1            0x5d  /*  93 */   
#define j_dup2_x2            0x5e  /*  94 */   
#define j_swap               0x5f  /*  95 */   
#define j_iadd               0x60  /*  96 */   
#define j_ladd               0x61  /*  97 */   
#define j_fadd               0x62  /*  98 */   
#define j_dadd               0x63  /*  99 */   
#define j_isub               0x64  /* 100 */   
#define j_lsub               0x65  /* 101 */   
#define j_fsub               0x66  /* 102 */   
#define j_dsub               0x67  /* 103 */   
#define j_imul               0x68  /* 104 */   
#define j_lmul               0x69  /* 105 */   
#define j_fmul               0x6a  /* 106 */   
#define j_dmul               0x6b  /* 107 */   
#define j_idiv               0x6c  /* 108 */   
#define j_ldiv               0x6d  /* 109 */   
#define j_fdiv               0x6e  /* 110 */   
#define j_ddiv               0x6f  /* 111 */   
#define j_irem               0x70  /* 112 */   
#define j_lrem               0x71  /* 113 */   
#define j_frem               0x72  /* 114 */   
#define j_drem               0x73  /* 115 */   
#define j_ineg               0x74  /* 116 */   
#define j_lneg               0x75  /* 117 */   
#define j_fneg               0x76  /* 118 */   
#define j_dneg               0x77  /* 119 */   
#define j_ishl               0x78  /* 120 */   
#define j_lshl               0x79  /* 121 */   
#define j_ishr               0x7a  /* 122 */   
#define j_lshr               0x7b  /* 123 */   
#define j_iushr              0x7c  /* 124 */   
#define j_lushr              0x7d  /* 125 */   
#define j_iand               0x7e  /* 126 */   
#define j_land               0x7f  /* 127 */   
#define j_ior                0x80  /* 128 */   
#define j_lor                0x81  /* 129 */   
#define j_ixor               0x82  /* 130 */   
#define j_lxor               0x83  /* 131 */   
#define j_iinc               0x84  /* 132 */   
#define j_i2l                0x85  /* 133 */   
#define j_i2f                0x86  /* 134 */   
#define j_i2d                0x87  /* 135 */   
#define j_l2i                0x88  /* 136 */   
#define j_l2f                0x89  /* 137 */   
#define j_l2d                0x8a  /* 138 */   
#define j_f2i                0x8b  /* 139 */   
#define j_f2l                0x8c  /* 140 */   
#define j_f2d                0x8d  /* 141 */   
#define j_d2i                0x8e  /* 142 */   
#define j_d2l                0x8f  /* 143 */   
#define j_d2f                0x90  /* 144 */   
#define j_i2b                0x91  /* 145 */   
#define j_i2c                0x92  /* 146 */   
#define j_i2s                0x93  /* 147 */   
#define j_lcmp               0x94  /* 148 */   
#define j_fcmpl              0x95  /* 149 */   
#define j_fcmpg              0x96  /* 150 */   
#define j_dcmpl              0x97  /* 151 */   
#define j_dcmpg              0x98  /* 152 */   
#define j_ifeq               0x99  /* 153 */   
#define j_ifne               0x9a  /* 154 */   
#define j_iflt               0x9b  /* 155 */   
#define j_ifge               0x9c  /* 156 */   
#define j_ifgt               0x9d  /* 157 */   
#define j_ifle               0x9e  /* 158 */   
#define j_if_icmpeq          0x9f  /* 159 */   
#define j_if_icmpne          0xa0  /* 160 */   
#define j_if_icmplt          0xa1  /* 161 */   
#define j_if_icmpge          0xa2  /* 162 */   
#define j_if_icmpgt          0xa3  /* 163 */   
#define j_if_icmple          0xa4  /* 164 */   
#define j_if_acmpeq          0xa5  /* 165 */   
#define j_if_acmpne          0xa6  /* 166 */   
#define j_goto               0xa7  /* 167 */   
#define j_jsr                0xa8  /* 168 */   
#define j_ret                0xa9  /* 169 */   
#define j_tableswitch        0xaa  /* 170 */   
#define j_lookupswitch       0xab  /* 171 */   
#define j_ireturn            0xac  /* 172 */   
#define j_lreturn            0xad  /* 173 */   
#define j_freturn            0xae  /* 174 */   
#define j_dreturn            0xaf  /* 175 */   
#define j_areturn            0xb0  /* 176 */   
#define j_return             0xb1  /* 177 */   
#define j_getstatic          0xb2  /* 178 */   
#define j_putstatic          0xb3  /* 179 */   
#define j_getfield           0xb4  /* 180 */   
#define j_putfield           0xb5  /* 181 */   
#define j_invokevirtual      0xb6  /* 182 */   
#define j_invokespecial      0xb7  /* 183 */   
#define j_invokestatic       0xb8  /* 184 */   
#define j_invokeinterface    0xb9  /* 185 */   
#define j_invokedynamic      0xba  /* 186 */   
#define j_new                0xbb  /* 187 */   
#define j_newarray           0xbc  /* 188 */   
#define j_anewarray          0xbd  /* 189 */   
#define j_arraylength        0xbe  /* 190 */   
#define j_athrow             0xbf  /* 191 */   
#define j_checkcast          0xc0  /* 192 */   
#define j_instanceof         0xc1  /* 193 */   
#define j_monitorenter       0xc2  /* 194 */   
#define j_monitorexit        0xc3  /* 195 */   
#define j_wide               0xc4  /* 196 */   
#define j_multianewarray     0xc5  /* 197 */   
#define j_ifnull             0xc6  /* 198 */   
#define j_ifnonnull          0xc7  /* 199 */   
#define j_goto_w             0xc8  /* 200 */   
#define j_jsr_w              0xc9  /* 201 */   
#define j_breakpoint         0xca  /* 202 */   
#define j_impdep1            0xfe  /* 254 */   
#define j_impdep2            0xff  /* 255 */   

#endif